{"year":425,"year_label":"425年","polity_count":10,"polities":[{"polity_id":"polity_0011","polity_name":"仇池","polity_aliases":"","macro_period":"魏晋南北朝","dynasty_name":"五胡十六国外政权","polity_type":"政权/国家","polity_start_year":184,"polity_end_year":443,"capital_modern_raw":"","modern_admin_units_raw":"","ruling_family_or_clan":"","ethnicity_or_group":"","founder":"","last_ruler":"","destroyed_by_or_successor":"","polity_source_titles":"《魏书》/《宋书》","polity_source_urls":"https://zh.wikipedia.org/wiki/%E4%BA%94%E8%83%A1%E5%8D%81%E5%85%AD%E5%9B%BD%E5%90%9B%E4%B8%BB%E5%88%97%E8%A1%A8","polity_source_raw":"443年后仇池为北魏所灭","confidence_score":90,"rulers":[],"capitals":[],"active_capital_event_ids":[],"has_capital_migration_in_year":false,"capital_quality":{"status":"missing","label":"暂无可解析都城资料","has_dispute":false,"lowest_confidence_score":null,"location_precision":"unknown","source_status":"missing"},"territory":{"geometry_ref":null,"territory_status":"missing","territory_method":"modern_admin_approximation","approx_area_km2":null,"match_confidence":0,"matched_admin_ids":[],"matched_admin_units":[],"source_text":"","match_source":"modern_admin_units_raw","confidence_note":"","label":"现代省级行政边界拼合，非历史精确边界"},"quality":{"confidence_score":90,"has_dispute":false,"has_unmatched_ruler":true}},{"polity_id":"polity_0017","polity_name":"刘宋","polity_aliases":"宋","macro_period":"魏晋南北朝","dynasty_name":"南北朝","polity_type":"王朝/政权","polity_start_year":420,"polity_end_year":479,"capital_modern_raw":"","modern_admin_units_raw":"","ruling_family_or_clan":"劉 | 彭城劉氏","ethnicity_or_group":"漢","founder":"武帝 劉裕","last_ruler":"順帝 劉準","destroyed_by_or_successor":"","polity_source_titles":"《宋书》/《南史》","polity_source_urls":"https://zh.wikipedia.org/wiki/%E4%B8%AD%E5%9B%BD%E6%9C%9D%E4%BB%A3 | https://dict.revised.moe.edu.tw/appendix.jsp?ID=2&la=0&page=*&powerMode=0 | https://zh.wikipedia.org/wiki/%E5%8D%97%E5%8C%97%E6%9C%9D | https://zh.wikipedia.org/wiki/%E5%8D%97%E5%8C%97%E6%9C%9D%E5%90%9B%E4%B8%BB%E5%88%97%E8%A1%A8","polity_source_raw":"479年宋顺帝禅位于萧道成，刘宋灭亡","confidence_score":100,"rulers":[{"ruler_id":"ruler_00118","ruler_name":"文帝","ruler_title":"文帝","ruler_temple_name":"","ruler_posthumous_name":"","ruler_personal_name":"","era_names":"","ruler_reign_start_year":424,"ruler_reign_end_year":452,"ruler_source_title":"教育部《重编国语辞典修订本》中国历代帝王年表","ruler_source_url":"https://dict.revised.moe.edu.tw/appendix.jsp?ID=2&la=0&page=*&powerMode=0","ruler_confidence_score":86}],"capitals":[],"active_capital_event_ids":[],"has_capital_migration_in_year":false,"capital_quality":{"status":"missing","label":"暂无可解析都城资料","has_dispute":false,"lowest_confidence_score":null,"location_precision":"unknown","source_status":"missing"},"territory":{"geometry_ref":null,"territory_status":"missing","territory_method":"modern_admin_approximation","approx_area_km2":null,"match_confidence":0,"matched_admin_ids":[],"matched_admin_units":[],"source_text":"","match_source":"modern_admin_units_raw","confidence_note":"","label":"现代省级行政边界拼合，非历史精确边界"},"quality":{"confidence_score":100,"has_dispute":true,"has_unmatched_ruler":false}},{"polity_id":"polity_0024","polity_name":"北凉","polity_aliases":"","macro_period":"魏晋南北朝","dynasty_name":"五胡十六国","polity_type":"王朝/政权","polity_start_year":397,"polity_end_year":439,"capital_modern_raw":"","modern_admin_units_raw":"甘肅西部、部分寧夏、部分新疆、部分青海","ruling_family_or_clan":"沮渠","ethnicity_or_group":"盧水胡","founder":"段業","last_ruler":"沮渠牧犍","destroyed_by_or_successor":"北魏、柔然","polity_source_titles":"《魏书》/《晋书》","polity_source_urls":"https://zh.wikipedia.org/wiki/%E4%B8%AD%E5%9B%BD%E6%9C%9D%E4%BB%A3 | https://zh.wikipedia.org/wiki/%E4%BA%94%E8%83%A1%E5%8D%81%E5%85%AD%E5%9B%BD | https://zh.wikipedia.org/wiki/%E4%BA%94%E8%83%A1%E5%8D%81%E5%85%AD%E5%9B%BD%E5%90%9B%E4%B8%BB%E5%88%97%E8%A1%A8","polity_source_raw":"439年被北魏太武帝拓跋焘所灭","confidence_score":100,"rulers":[{"ruler_id":"ruler_00142","ruler_name":"沮渠蒙遜","ruler_title":"武宣王","ruler_temple_name":"太祖","ruler_posthumous_name":"武宣王","ruler_personal_name":"沮渠蒙遜","era_names":"永安 玄始 承玄 義和","ruler_reign_start_year":401,"ruler_reign_end_year":433,"ruler_source_title":"五胡十六国君主列表 - 维基百科","ruler_source_url":"https://zh.wikipedia.org/wiki/%E4%BA%94%E8%83%A1%E5%8D%81%E5%85%AD%E5%9B%BD%E5%90%9B%E4%B8%BB%E5%88%97%E8%A1%A8","ruler_confidence_score":65}],"capitals":[],"active_capital_event_ids":[],"has_capital_migration_in_year":false,"capital_quality":{"status":"missing","label":"暂无可解析都城资料","has_dispute":false,"lowest_confidence_score":null,"location_precision":"unknown","source_status":"missing"},"territory":{"geometry_ref":"territories/approx_polities.geojson#polity_0024","territory_status":"matched","territory_method":"modern_admin_approximation","approx_area_km2":2799957.7,"match_confidence":72,"matched_admin_ids":["CN-GS","CN-NX","CN-QH","CN-XJ"],"matched_admin_units":["甘肃省","宁夏回族自治区","青海省","新疆维吾尔自治区"],"source_text":"甘肅西部、部分寧夏、部分新疆、部分青海","geometry_source":"input/v03/admin_boundaries/china_adm1_normalized.geojson","geometry_source_license":"Public Domain","geometry_source_attribution":"geoBoundaries / Wikimedia Commons","match_source":"modern_admin_units_raw","confidence_note":"","geometry_coordinate_count":829,"generated_at":"2026-05-15T14:53:56+00:00","label":"现代省级行政边界拼合，非历史精确边界","centroid":[91.19432363900006,40.43096853450007]},"quality":{"confidence_score":100,"has_dispute":false,"has_unmatched_ruler":false}},{"polity_id":"polity_0028","polity_name":"北燕","polity_aliases":"","macro_period":"魏晋南北朝","dynasty_name":"五胡十六国","polity_type":"王朝/政权","polity_start_year":407,"polity_end_year":436,"capital_modern_raw":"","modern_admin_units_raw":"遼寧、河北","ruling_family_or_clan":"馮","ethnicity_or_group":"漢 | 高句麗、漢","founder":"慕容云（后称高云） | 高雲 或 馮跋","last_ruler":"馮弘","destroyed_by_or_successor":"北魏","polity_source_titles":"《晋书·冯跋等载记》","polity_source_urls":"https://zh.wikipedia.org/wiki/%E4%B8%AD%E5%9B%BD%E6%9C%9D%E4%BB%A3 | https://zh.wikipedia.org/wiki/%E4%BA%94%E8%83%A1%E5%8D%81%E5%85%AD%E5%9B%BD | https://zh.wikipedia.org/wiki/%E4%BA%94%E8%83%A1%E5%8D%81%E5%85%AD%E5%9B%BD%E5%90%9B%E4%B8%BB%E5%88%97%E8%A1%A8","polity_source_raw":"436年被北魏所灭","confidence_score":100,"rulers":[{"ruler_id":"ruler_00165","ruler_name":"馮跋","ruler_title":"文成皇帝","ruler_temple_name":"太祖","ruler_posthumous_name":"文成皇帝","ruler_personal_name":"馮跋","era_names":"太平","ruler_reign_start_year":409,"ruler_reign_end_year":430,"ruler_source_title":"五胡十六国君主列表 - 维基百科","ruler_source_url":"https://zh.wikipedia.org/wiki/%E4%BA%94%E8%83%A1%E5%8D%81%E5%85%AD%E5%9B%BD%E5%90%9B%E4%B8%BB%E5%88%97%E8%A1%A8","ruler_confidence_score":65}],"capitals":[],"active_capital_event_ids":[],"has_capital_migration_in_year":false,"capital_quality":{"status":"missing","label":"暂无可解析都城资料","has_dispute":false,"lowest_confidence_score":null,"location_precision":"unknown","source_status":"missing"},"territory":{"geometry_ref":"territories/approx_polities.geojson#polity_0028","territory_status":"matched","territory_method":"modern_admin_approximation","approx_area_km2":334941.3,"match_confidence":86,"matched_admin_ids":["CN-HE","CN-LN"],"matched_admin_units":["河北省","辽宁省"],"source_text":"遼寧、河北","geometry_source":"input/v03/admin_boundaries/china_adm1_normalized.geojson","geometry_source_license":"Public Domain","geometry_source_attribution":"geoBoundaries / Wikimedia Commons","match_source":"modern_admin_units_raw","confidence_note":"","geometry_coordinate_count":326,"generated_at":"2026-05-15T14:53:56+00:00","label":"现代省级行政边界拼合，非历史精确边界","centroid":[119.71861168900006,39.87015809950003]},"quality":{"confidence_score":100,"has_dispute":false,"has_unmatched_ruler":false}},{"polity_id":"polity_0030","polity_name":"北魏","polity_aliases":"","macro_period":"魏晋南北朝","dynasty_name":"南北朝","polity_type":"王朝/政权","polity_start_year":386,"polity_end_year":534,"capital_modern_raw":"","modern_admin_units_raw":"","ruling_family_or_clan":"拓跋 | 拓跋氏→河南元氏","ethnicity_or_group":"鮮卑","founder":"道武帝 拓跋珪","last_ruler":"孝武帝 元修","destroyed_by_or_successor":"","polity_source_titles":"《魏书》/《北史》","polity_source_urls":"https://zh.wikipedia.org/wiki/%E4%B8%AD%E5%9B%BD%E6%9C%9D%E4%BB%A3 | https://dict.revised.moe.edu.tw/appendix.jsp?ID=2&la=0&page=*&powerMode=0 | https://zh.wikipedia.org/wiki/%E5%8D%97%E5%8C%97%E6%9C%9D | https://zh.wikipedia.org/wiki/%E5%8D%97%E5%8C%97%E6%9C%9D%E5%90%9B%E4%B8%BB%E5%88%97%E8%A1%A8","polity_source_raw":"534年孝武帝西奔长安，北魏正式分裂为东魏与西魏","confidence_score":100,"rulers":[{"ruler_id":"ruler_00177","ruler_name":"太武帝","ruler_title":"太武帝","ruler_temple_name":"","ruler_posthumous_name":"","ruler_personal_name":"","era_names":"","ruler_reign_start_year":424,"ruler_reign_end_year":452,"ruler_source_title":"教育部《重编国语辞典修订本》中国历代帝王年表","ruler_source_url":"https://dict.revised.moe.edu.tw/appendix.jsp?ID=2&la=0&page=*&powerMode=0","ruler_confidence_score":86},{"ruler_id":"ruler_00186","ruler_name":"拓跋焘","ruler_title":"太武皇帝","ruler_temple_name":"世祖","ruler_posthumous_name":"太武皇帝","ruler_personal_name":"拓跋焘","era_names":"始光","ruler_reign_start_year":424,"ruler_reign_end_year":452,"ruler_source_title":"南北朝君主列表 - 维基百科","ruler_source_url":"https://zh.wikipedia.org/wiki/%E5%8D%97%E5%8C%97%E6%9C%9D%E5%90%9B%E4%B8%BB%E5%88%97%E8%A1%A8","ruler_confidence_score":65}],"capitals":[{"capital_event_id":"capital_0014","polity_id":"polity_0030","polity_name":"北魏","capital_name_historical":"平城","capital_name_modern":"山西大同","valid_from_year":398,"valid_from_label":"398年","valid_to_year":493,"valid_to_label":"493年","longitude":113.3,"latitude":40.0768,"is_primary":true,"event_type":"relocation","location_precision":"city","source_titles":"《魏书》/《北史》","source_urls":"https://zh.wikipedia.org/wiki/%E5%B9%B3%E5%9F%8E","source_raw":"北魏迁都平城；坐标按今大同城市近似","confidence_score":80,"confidence_note":"迁都年份明确；城市级坐标","is_disputed":false}],"active_capital_event_ids":["capital_0014"],"has_capital_migration_in_year":false,"capital_quality":{"status":"present","label":"已解析当前有效都城","has_dispute":false,"lowest_confidence_score":80,"location_precision":"city","source_status":"present"},"territory":{"geometry_ref":null,"territory_status":"missing","territory_method":"modern_admin_approximation","approx_area_km2":null,"match_confidence":0,"matched_admin_ids":[],"matched_admin_units":[],"source_text":"","match_source":"modern_admin_units_raw","confidence_note":"","label":"现代省级行政边界拼合，非历史精确边界"},"quality":{"confidence_score":100,"has_dispute":true,"has_unmatched_ruler":false}},{"polity_id":"polity_0043","polity_name":"后仇池","polity_aliases":"","macro_period":"魏晋南北朝","dynasty_name":"五胡十六国外政权","polity_type":"割据政权/国家","polity_start_year":385,"polity_end_year":443,"capital_modern_raw":"","modern_admin_units_raw":"陇西、汉中、天水一带","ruling_family_or_clan":"","ethnicity_or_group":"氐","founder":"杨定","last_ruler":"杨保炽","destroyed_by_or_successor":"北魏","polity_source_titles":"《魏书》/《宋书》","polity_source_urls":"https://zh.wikipedia.org/wiki/%E4%BA%94%E8%83%A1%E5%8D%81%E5%85%AD%E5%9B%BD","polity_source_raw":"443年被北魏所灭","confidence_score":90,"rulers":[],"capitals":[],"active_capital_event_ids":[],"has_capital_migration_in_year":false,"capital_quality":{"status":"missing","label":"暂无可解析都城资料","has_dispute":false,"lowest_confidence_score":null,"location_precision":"unknown","source_status":"missing"},"territory":{"geometry_ref":null,"territory_status":"missing","territory_method":"modern_admin_approximation","approx_area_km2":null,"match_confidence":0,"matched_admin_ids":[],"matched_admin_units":[],"source_text":"陇西、汉中、天水一带","match_source":"modern_admin_units_raw","confidence_note":"","label":"现代省级行政边界拼合，非历史精确边界"},"quality":{"confidence_score":90,"has_dispute":false,"has_unmatched_ruler":true}},{"polity_id":"polity_0070","polity_name":"扶余","polity_aliases":"","macro_period":"魏晋南北朝","dynasty_name":"五胡十六国外政权","polity_type":"政权/国家","polity_start_year":-86,"polity_end_year":494,"capital_modern_raw":"","modern_admin_units_raw":"","ruling_family_or_clan":"","ethnicity_or_group":"","founder":"","last_ruler":"","destroyed_by_or_successor":"","polity_source_titles":"《三国史记》/《魏书》","polity_source_urls":"https://zh.wikipedia.org/wiki/%E4%BA%94%E8%83%A1%E5%8D%81%E5%85%AD%E5%9B%BD%E5%90%9B%E4%B8%BB%E5%88%97%E8%A1%A8","polity_source_raw":"494年被高句丽所灭","confidence_score":90,"rulers":[],"capitals":[],"active_capital_event_ids":[],"has_capital_migration_in_year":false,"capital_quality":{"status":"missing","label":"暂无可解析都城资料","has_dispute":false,"lowest_confidence_score":null,"location_precision":"unknown","source_status":"missing"},"territory":{"geometry_ref":null,"territory_status":"missing","territory_method":"modern_admin_approximation","approx_area_km2":null,"match_confidence":0,"matched_admin_ids":[],"matched_admin_units":[],"source_text":"","match_source":"modern_admin_units_raw","confidence_note":"","label":"现代省级行政边界拼合，非历史精确边界"},"quality":{"confidence_score":90,"has_dispute":false,"has_unmatched_ruler":true}},{"polity_id":"polity_0078","polity_name":"柔然","polity_aliases":"","macro_period":"魏晋南北朝","dynasty_name":"五胡十六国外政权","polity_type":"政权/国家","polity_start_year":402,"polity_end_year":555,"capital_modern_raw":"","modern_admin_units_raw":"","ruling_family_or_clan":"","ethnicity_or_group":"","founder":"","last_ruler":"","destroyed_by_or_successor":"","polity_source_titles":"《魏书》/《北史》","polity_source_urls":"https://zh.wikipedia.org/wiki/%E4%BA%94%E8%83%A1%E5%8D%81%E5%85%AD%E5%9B%BD%E5%90%9B%E4%B8%BB%E5%88%97%E8%A1%A8","polity_source_raw":"555年被突厥彻底消灭","confidence_score":95,"rulers":[],"capitals":[],"active_capital_event_ids":[],"has_capital_migration_in_year":false,"capital_quality":{"status":"missing","label":"暂无可解析都城资料","has_dispute":false,"lowest_confidence_score":null,"location_precision":"unknown","source_status":"missing"},"territory":{"geometry_ref":null,"territory_status":"missing","territory_method":"modern_admin_approximation","approx_area_km2":null,"match_confidence":0,"matched_admin_ids":[],"matched_admin_units":[],"source_text":"","match_source":"modern_admin_units_raw","confidence_note":"","label":"现代省级行政边界拼合，非历史精确边界"},"quality":{"confidence_score":95,"has_dispute":false,"has_unmatched_ruler":true}},{"polity_id":"polity_0113","polity_name":"胡夏","polity_aliases":"","macro_period":"魏晋南北朝","dynasty_name":"五胡十六国","polity_type":"王朝/政权","polity_start_year":407,"polity_end_year":431,"capital_modern_raw":"","modern_admin_units_raw":"陕西、部分内蒙古","ruling_family_or_clan":"赫連","ethnicity_or_group":"匈奴 | 匈奴铁弗","founder":"赫連勃勃","last_ruler":"赫連定","destroyed_by_or_successor":"吐谷浑、北魏","polity_source_titles":"《晋书·赫连勃勃载记》","polity_source_urls":"https://zh.wikipedia.org/wiki/%E4%B8%AD%E5%9B%BD%E6%9C%9D%E4%BB%A3 | https://zh.wikipedia.org/wiki/%E4%BA%94%E8%83%A1%E5%8D%81%E5%85%AD%E5%9B%BD | https://zh.wikipedia.org/wiki/%E4%BA%94%E8%83%A1%E5%8D%81%E5%85%AD%E5%9B%BD%E5%90%9B%E4%B8%BB%E5%88%97%E8%A1%A8","polity_source_raw":"431年赫连定被吐谷浑俘获送交北魏，胡夏灭亡","confidence_score":100,"rulers":[{"ruler_id":"ruler_00619","ruler_name":"赫連勃勃","ruler_title":"武烈皇帝","ruler_temple_name":"世祖","ruler_posthumous_name":"武烈皇帝","ruler_personal_name":"赫連勃勃","era_names":"龍昇 鳳翔 昌武 真興","ruler_reign_start_year":407,"ruler_reign_end_year":425,"ruler_source_title":"五胡十六国君主列表 - 维基百科","ruler_source_url":"https://zh.wikipedia.org/wiki/%E4%BA%94%E8%83%A1%E5%8D%81%E5%85%AD%E5%9B%BD%E5%90%9B%E4%B8%BB%E5%88%97%E8%A1%A8","ruler_confidence_score":65},{"ruler_id":"ruler_00621","ruler_name":"赫連昌","ruler_title":"","ruler_temple_name":"","ruler_posthumous_name":"","ruler_personal_name":"赫連昌","era_names":"承光","ruler_reign_start_year":425,"ruler_reign_end_year":428,"ruler_source_title":"五胡十六国君主列表 - 维基百科","ruler_source_url":"https://zh.wikipedia.org/wiki/%E4%BA%94%E8%83%A1%E5%8D%81%E5%85%AD%E5%9B%BD%E5%90%9B%E4%B8%BB%E5%88%97%E8%A1%A8","ruler_confidence_score":65}],"capitals":[],"active_capital_event_ids":[],"has_capital_migration_in_year":false,"capital_quality":{"status":"missing","label":"暂无可解析都城资料","has_dispute":false,"lowest_confidence_score":null,"location_precision":"unknown","source_status":"missing"},"territory":{"geometry_ref":"territories/approx_polities.geojson#polity_0113","territory_status":"matched","territory_method":"modern_admin_approximation","approx_area_km2":1334829.9,"match_confidence":72,"matched_admin_ids":["CN-NM","CN-SN"],"matched_admin_units":["内蒙古自治区","陕西省"],"source_text":"陕西、部分内蒙古","geometry_source":"input/v03/admin_boundaries/china_adm1_normalized.geojson","geometry_source_license":"Public Domain","geometry_source_attribution":"geoBoundaries / Wikimedia Commons","match_source":"modern_admin_units_raw","confidence_note":"","geometry_coordinate_count":542,"generated_at":"2026-05-15T14:53:56+00:00","label":"现代省级行政边界拼合，非历史精确边界","centroid":[111.73707906650006,42.65572641950007]},"quality":{"confidence_score":100,"has_dispute":false,"has_unmatched_ruler":false}},{"polity_id":"polity_0136","polity_name":"西秦","polity_aliases":"","macro_period":"魏晋南北朝","dynasty_name":"五胡十六国","polity_type":"王朝/政权","polity_start_year":385,"polity_end_year":431,"capital_modern_raw":"","modern_admin_units_raw":"甘肅东部","ruling_family_or_clan":"乞伏","ethnicity_or_group":"鮮卑","founder":"乞伏國仁","last_ruler":"乞伏慕末 | 乞伏暮末","destroyed_by_or_successor":"胡夏","polity_source_titles":"《晋书·乞伏国仁等载记》","polity_source_urls":"https://zh.wikipedia.org/wiki/%E4%B8%AD%E5%9B%BD%E6%9C%9D%E4%BB%A3 | https://zh.wikipedia.org/wiki/%E4%BA%94%E8%83%A1%E5%8D%81%E5%85%AD%E5%9B%BD | https://zh.wikipedia.org/wiki/%E4%BA%94%E8%83%A1%E5%8D%81%E5%85%AD%E5%9B%BD%E5%90%9B%E4%B8%BB%E5%88%97%E8%A1%A8","polity_source_raw":"431年被胡夏(赫连定)所灭","confidence_score":95,"rulers":[{"ruler_id":"ruler_00712","ruler_name":"乞伏熾磐","ruler_title":"文昭王","ruler_temple_name":"太祖","ruler_posthumous_name":"文昭王","ruler_personal_name":"乞伏熾磐","era_names":"永康 建弘","ruler_reign_start_year":412,"ruler_reign_end_year":428,"ruler_source_title":"五胡十六国君主列表 - 维基百科","ruler_source_url":"https://zh.wikipedia.org/wiki/%E4%BA%94%E8%83%A1%E5%8D%81%E5%85%AD%E5%9B%BD%E5%90%9B%E4%B8%BB%E5%88%97%E8%A1%A8","ruler_confidence_score":65}],"capitals":[],"active_capital_event_ids":[],"has_capital_migration_in_year":false,"capital_quality":{"status":"missing","label":"暂无可解析都城资料","has_dispute":false,"lowest_confidence_score":null,"location_precision":"unknown","source_status":"missing"},"territory":{"geometry_ref":"territories/approx_polities.geojson#polity_0136","territory_status":"matched","territory_method":"modern_admin_approximation","approx_area_km2":422125.2,"match_confidence":86,"matched_admin_ids":["CN-GS"],"matched_admin_units":["甘肃省"],"source_text":"甘肅东部","geometry_source":"input/v03/admin_boundaries/china_adm1_normalized.geojson","geometry_source_license":"Public Domain","geometry_source_attribution":"geoBoundaries / Wikimedia Commons","match_source":"modern_admin_units_raw","confidence_note":"","geometry_coordinate_count":260,"generated_at":"2026-05-15T14:53:56+00:00","label":"现代省级行政边界拼合，非历史精确边界","centroid":[100.70013567550006,37.657088427000076]},"quality":{"confidence_score":95,"has_dispute":false,"has_unmatched_ruler":false}}],"capital_migrations":[],"has_capital_migration_in_year":false}
