{"year":-2172,"year_label":"前2172年","polity_count":1,"polities":[{"polity_id":"polity_ind_0002","polity_name":"成熟哈拉帕/印度河文明","polity_aliases":"Mature Harappan|Indus civilization","polity_display_name":"成熟哈拉帕/印度河文明","polity_name_disambiguation":"","polity_name_review_status":"verified","polity_name_risk_flags":"","polity_type":"civilization_complex","macro_period":"史前与原史时期","dynasty_name":"印度河文明","polity_start_year":-2600,"polity_end_year":-1900,"modern_admin_units_raw":"Pakistan Sindh/Punjab/Balochistan|India Gujarat/Rajasthan/Haryana","capital_historical_raw":"","capital_modern_raw":"","ruling_family_or_clan":"","ethnicity_or_group":"","founder":"","last_ruler":"","destroyed_by_or_successor":"","polity_source_titles":"Digital South Asia Library: A Historical Atlas of South Asia|NCERT Themes in Indian History, Part I|UNESCO World Heritage Centre: Dholavira, a Harappan City|Encyclopaedia Britannica: Indus civilization","polity_source_urls":"https://dsal.uchicago.edu/reference/schwartzberg/bootstrap_index.html|https://ncert.nic.in/textbook/pdf/lehs101.pdf|https://whc.unesco.org/en/list/1645|https://www.britannica.com/topic/Indus-civilization","polity_source_raw":"","is_nomadic":false,"is_steppe_origin":false,"capitals":[],"active_capital_event_ids":[],"has_capital_migration_in_year":false,"capital_quality":{"status":"missing","label":"missing","has_dispute":false,"lowest_confidence_score":null,"location_precision":"","source_status":"missing"},"territory":{"geometry_ref":"polity_ind_0002","territory_status":"matched","territory_method":"modern_admin_approximation","approx_area_km2":null,"match_confidence":70},"rulers":[],"confidence_score":78.0,"quality":{"confidence_score":78.0,"has_dispute":false,"has_unmatched_ruler":true}}],"capital_migrations":[],"historical_events":[],"historical_anecdotes":[],"historical_contexts":[]}